anfema_django_testutils/__init__.py
anfema_django_testutils/apps.py
anfema_django_testutils/checks.py
anfema_django_testutils/runner.py
anfema_django_testutils/settings.py
anfema_django_testutils/tags.py
anfema_django_testutils/testcases.py
anfema_django_testutils/contrib/__init__.py
anfema_django_testutils/contrib/fixtures/__init__.py
anfema_django_testutils/contrib/fixtures/apps.py
anfema_django_testutils/contrib/fixtures/checks.py
anfema_django_testutils/contrib/fixtures/settings.py
anfema_django_testutils/contrib/fixtures/finders/__init__.py
anfema_django_testutils/contrib/fixtures/finders/base.py
anfema_django_testutils/contrib/fixtures/finders/fixture.py
anfema_django_testutils/contrib/fixtures/finders/media.py
anfema_django_testutils/contrib/fixtures/management/__init__.py
anfema_django_testutils/contrib/fixtures/management/commands/__init__.py
anfema_django_testutils/contrib/fixtures/management/commands/collectfixturemedia.py
anfema_django_testutils/contrib/fixtures/management/commands/findfixture.py
anfema_django_testutils/contrib/fixtures/management/commands/findfixturemedia.py
anfema_django_testutils/static/css/test-results.css
anfema_django_testutils/static/js/test-results.js
anfema_django_testutils/templates/test-results-template.html
anfema_django_testutils-0.8.0.dist-info/LICENSE
anfema_django_testutils-0.8.0.dist-info/WHEEL
anfema_django_testutils-0.8.0.dist-info/METADATA
anfema_django_testutils-0.8.0.dist-info/RECORD
