Metadata-Version: 2.1
Name: anfema-django-testutils
Version: 0.8.0
Summary: Testrunner for django which covers html report and code coverage
Keywords: django,tests,coverage,testrunner
Requires-Python: >=3.9
Classifier: Framework :: Django :: 3.2
Classifier: Framework :: Django :: 4.1
Classifier: Framework :: Django :: 4.2
Classifier: Programming Language :: Python :: 3
Classifier: Programming Language :: Python :: 3.9
Classifier: Programming Language :: Python :: 3.10
Classifier: Programming Language :: Python :: 3.11
Classifier: License :: OSI Approved :: MIT License
Requires-Dist: django>=3.2
Requires-Dist: django-mathfilters
Requires-Dist: coverage[toml]
Requires-Dist: snapshottest
Requires-Dist: sphinx~=5.1 ; extra == "docs"
Requires-Dist: sphinx-autodoc-typehints ; extra == "docs"
Requires-Dist: sphinx_rtd_theme ; extra == "docs"
Requires-Dist: sphinx-copybutton ; extra == "docs"
Requires-Dist: m2r2 ; extra == "docs"
Requires-Dist: parametrize ; extra == "tests"
Project-URL: Documentation, https://anfema.github.io/anfema-django-testutils
Project-URL: Source, https://github.com/anfema/anfema-django-testutils
Provides-Extra: docs
Provides-Extra: tests
